sgffp/__init__.py
sgffp/cli.py
sgffp/internal.py
sgffp/parsers.py
sgffp/reader.py
sgffp/writer.py
sgffp/models/__init__.py
sgffp/models/alignment.py
sgffp/models/base.py
sgffp/models/feature.py
sgffp/models/history.py
sgffp/models/notes.py
sgffp/models/primer.py
sgffp/models/properties.py
sgffp/models/sequence.py
sgffp/models/trace.py
sgffp-0.13.0.dist-info/METADATA
sgffp-0.13.0.dist-info/WHEEL
sgffp-0.13.0.dist-info/entry_points.txt
sgffp-0.13.0.dist-info/licenses/LICENSE
sgffp-0.13.0.dist-info/RECORD
