Metadata-Version: 2.4
Name: sgffp
Version: 0.13.0
Summary: Read, write, and manipulate SnapGene files (.dna, .rna, .prot)
Project-URL: Homepage, https://github.com/merv1n34k/sgffp
Project-URL: Repository, https://github.com/merv1n34k/sgffp
Project-URL: Issues, https://github.com/merv1n34k/sgffp/issues
Author-email: Oleksii Stroganov <merv1n@proton.me>
License: MIT
License-File: LICENSE
Keywords: bioinformatics,dna,molecular-biology,parser,protein,rna,snapgene
Classifier: Development Status :: 4 - Beta
Classifier: Intended Audience :: Developers
Classifier: Intended Audience :: Science/Research
Classifier: License :: OSI Approved :: MIT License
Classifier: Programming Language :: Python :: 3.12
Classifier: Topic :: File Formats
Classifier: Topic :: Scientific/Engineering :: Bio-Informatics
Requires-Python: >=3.12
Requires-Dist: biopython>=1.86
Requires-Dist: html2text>=2025.4.15
Requires-Dist: matplotlib>=3.10.7
Requires-Dist: numpy>=2.3.4
Requires-Dist: pandas>=2.3.3
Requires-Dist: xmltodict>=1.0.2
Provides-Extra: dev
Requires-Dist: pytest-cov>=4.0; extra == 'dev'
Requires-Dist: pytest>=8.0; extra == 'dev'
